pinyin_markdown/__init__.py
pinyin_markdown/numbered_accented.py
pinyin_markdown/pinyin_regex.py
pinyin_markdown/pinyinextension.py
pinyin_markdown-0.8.2.dist-info/DESCRIPTION.rst
pinyin_markdown-0.8.2.dist-info/METADATA
pinyin_markdown-0.8.2.dist-info/RECORD
pinyin_markdown-0.8.2.dist-info/WHEEL
pinyin_markdown-0.8.2.dist-info/metadata.json
pinyin_markdown-0.8.2.dist-info/top_level.txt
