Metadata-Version: 2.0
Name: pinyin-markdown
Version: 0.8.2
Summary: Type Chinese pinyin with tone numbers in Markdown. Get accented pinyin.
Home-page: https://github.com/bcaller/pinyin_markdown
Author: Ben Caller
Author-email: bcallergmai@l.com
License: AGPLv3
Keywords: pinyin chinese markdown
Platform: UNKNOWN
Classifier: Development Status :: 4 - Beta
Classifier: Environment :: Console
Classifier: Intended Audience :: Developers
Classifier: Programming Language :: Python
Classifier: Programming Language :: Python :: 3
Classifier: Programming Language :: Python :: 3.2
Classifier: Programming Language :: Python :: 3.4
Classifier: Programming Language :: Python :: 3.5
Classifier: Topic :: Internet :: WWW/HTTP :: Dynamic Content
Classifier: Topic :: Software Development :: Libraries :: Python Modules
Classifier: Topic :: Text Processing :: Filters
Classifier: Topic :: Text Processing :: Markup :: HTML
Classifier: License :: OSI Approved :: GNU Affero General Public License v3
Requires-Dist: markdown (>=2.5)
